yofx/__init__.py
yofx/cli.py
yofx/client.py
yofx/config.py
yofx/helpers.py
yofx/json.py
yofx/parse.py
yofx/types.py
yofx-0.1.1.post2.dist-info/entry_points.txt
yofx-0.1.1.post2.dist-info/WHEEL
yofx-0.1.1.post2.dist-info/METADATA
yofx-0.1.1.post2.dist-info/RECORD
