Metadata-Version: 2.1
Name: yofx
Version: 0.1.1.post2
Summary: 
Author: Carlo Holl
Author-email: carloholl@gmail.com
Requires-Python: >=3.6,<4.0
Classifier: Programming Language :: Python :: 3
Classifier: Programming Language :: Python :: 3.6
Classifier: Programming Language :: Python :: 3.7
Classifier: Programming Language :: Python :: 3.8
Classifier: Programming Language :: Python :: 3.9
Requires-Dist: pytz (>=2019.1)
Requires-Dist: requests (>=2.24.0,<3.0.0)
Requires-Dist: typing_extensions (>=3.7.4,<4.0.0)
